moat/link/server/__init__.py
moat/link/server/_cfg.yaml
moat/link/server/_main.py
moat/link/server/_server.py
moat_link_server-0.3.25.dist-info/licenses/LICENSE.txt
moat_link_server-0.3.25.dist-info/METADATA
moat_link_server-0.3.25.dist-info/WHEEL
moat_link_server-0.3.25.dist-info/top_level.txt
moat_link_server-0.3.25.dist-info/RECORD
