Metadata-Version: 2.4
Name: moat-link-server
Version: 0.3.25
Summary: Storage for messages between MoaT instances
Author-email: Matthias Urlichs <matthias@urlichs.de>
Project-URL: homepage, https://m-o-a-t.org
Project-URL: repository, https://github.com/M-o-a-T/moat
Keywords: MoaT
Classifier: Intended Audience :: Developers
Classifier: Programming Language :: Python :: 3
Classifier: Framework :: AsyncIO
Classifier: Framework :: Trio
Classifier: Framework :: AnyIO
Classifier: Development Status :: 4 - Beta
Requires-Python: >=3.8
License-File: LICENSE.txt
Requires-Dist: anyio~=4.2
Requires-Dist: asyncactor~=0.27.0
Requires-Dist: asyncclick
Requires-Dist: attrs
Requires-Dist: ruyaml
Requires-Dist: simpleeval
Requires-Dist: moat-util~=0.61.1
Requires-Dist: moat-lib-rpc~=0.4.6
Requires-Dist: moat-lib-codec~=0.4.7
Requires-Dist: moat-link~=0.2.35
Requires-Dist: moat-lib-mqtt~=0.8.0
Requires-Dist: moat-lib-config~=0.1.0
Dynamic: license-file
